oldwebdock/__init__.py
oldwebdock/exceptions.py
oldwebdock/webdock.py
oldwebdock/tests/TestWebdock.py
webdock/__init__.py
webdock/test/__init__.py
webdock/test/test_account.py
webdock/test/test_events.py
webdock/test/test_hooks.py
webdock/test/test_images.py
webdock/test/test_locations.py
webdock/test/test_profiles.py
webdock/test/test_scripts.py
webdock/test/test_servers.py
webdock/test/test_shellusers.py
webdock/test/test_snapshots.py
webdock/test/test_sshkeys.py
webdock/webdock/__init__.py
webdock/webdock/account.py
webdock/webdock/events.py
webdock/webdock/hooks.py
webdock/webdock/images.py
webdock/webdock/locations.py
webdock/webdock/operation.py
webdock/webdock/profiles.py
webdock/webdock/req.py
webdock/webdock/scripts.py
webdock/webdock/servers.py
webdock/webdock/shellusers.py
webdock/webdock/snapshots.py
webdock/webdock/sshkeys.py
webdock-1.0.4.dist-info/licenses/LICENCE
webdock-1.0.4.dist-info/METADATA
webdock-1.0.4.dist-info/WHEEL
webdock-1.0.4.dist-info/top_level.txt
webdock-1.0.4.dist-info/RECORD
